songsingergenerator/__init__.py
songsingergenerator/__main__.py
songsingergenerator/music.py
songsingergenerator-0.1.2.dist-info/LICENSE
songsingergenerator-0.1.2.dist-info/METADATA
songsingergenerator-0.1.2.dist-info/WHEEL
songsingergenerator-0.1.2.dist-info/entry_points.txt
songsingergenerator-0.1.2.dist-info/top_level.txt
songsingergenerator-0.1.2.dist-info/RECORD
