Metadata-Version: 2.1
Name: songsingergenerator
Version: 0.1.2
Summary: A fun Python package to generate random songs, select random singers, and find singers by name.
Author-email: solapis <your.email@example.com>
License: GNU GENERAL PUBLIC LICENSE
Project-URL: Homepage, https://github.com/software-students-spring2025/3-python-package-solapis/tree/main
Project-URL: Repository, https://github.com/software-students-spring2025/3-python-package-solapis.git
Keywords: python,package,music,singers,generator,fun
Classifier: Programming Language :: Python :: 3
Classifier: Intended Audience :: Developers
Classifier: License :: OSI Approved :: MIT License
Classifier: Operating System :: OS Independent
Requires-Python: >=3.7
License-File: LICENSE
Provides-Extra: dev
Requires-Dist: pytest; extra == "dev"
